MANIFEST.in
setup.cfg
setup.py
kenessa/__init__.py
kenessa/command_line.py
kenessa/kenessa.db
kenessa.egg-info/PKG-INFO
kenessa.egg-info/SOURCES.txt
kenessa.egg-info/dependency_links.txt
kenessa.egg-info/entry_points.txt
kenessa.egg-info/not-zip-safe
kenessa.egg-info/top_level.txt