Metadata-Version: 1.1
Name: kenessa
Version: 0.2.2
Summary: Rwanda Administrative Location
Home-page: https://github.com/rmuhire/kenessa
Author: Remy Muhire
Author-email: rmuhire@exuus.com
License: MIT
Keywords: rwanda administrative location
Platform: UNKNOWN
Classifier: Programming Language :: Python
Classifier: Programming Language :: Python :: 2.6
Classifier: Programming Language :: Python :: 2.7
Classifier: Development Status :: 4 - Beta
Classifier: Environment :: Other Environment
Classifier: Intended Audience :: Developers
Classifier: Intended Audience :: Education
Classifier: License :: OSI Approved :: GNU General Public License (GPL)
Classifier: Operating System :: OS Independent
Classifier: Topic :: Software Development :: Libraries :: Python Modules
